verilog/hardware/processor/improved_verilog/instruction_mem.v
/*
	Authored 2018-2019, Ryan Voo.

	All rights reserved.
	Redistribution and use in source and binary forms, with or without
	modification, are permitted provided that the following conditions
	are met:

	*	Redistributions of source code must retain the above
		copyright notice, this list of conditions and the following
		disclaimer.

	*	Redistributions in binary form must reproduce the above
		copyright notice, this list of conditions and the following
		disclaimer in the documentation and/or other materials
		provided with the distribution.

	*	Neither the name of the author nor the names of its
		contributors may be used to endorse or promote products
		derived from this software without specific prior written
		permission.

	THIS SOFTWARE IS PROVIDED BY THE COPYRIGHT HOLDERS AND CONTRIBUTORS
	"AS IS" AND ANY EXPRESS OR IMPLIED WARRANTIES, INCLUDING, BUT NOT
	LIMITED TO, THE IMPLIED WARRANTIES OF MERCHANTABILITY AND FITNESS
	FOR A PARTICULAR PURPOSE ARE DISCLAIMED. IN NO EVENT SHALL THE
	COPYRIGHT OWNER OR CONTRIBUTORS BE LIABLE FOR ANY DIRECT, INDIRECT,
	INCIDENTAL, SPECIAL, EXEMPLARY, OR CONSEQUENTIAL DAMAGES (INCLUDING,
	BUT NOT LIMITED TO, PROCUREMENT OF SUBSTITUTE GOODS OR SERVICES;
	LOSS OF USE, DATA, OR PROFITS; OR BUSINESS INTERRUPTION) HOWEVER
	CAUSED AND ON ANY THEORY OF LIABILITY, WHETHER IN CONTRACT, STRICT
	LIABILITY, OR TORT (INCLUDING NEGLIGENCE OR OTHERWISE) ARISING IN
	ANY WAY OUT OF THE USE OF THIS SOFTWARE, EVEN IF ADVISED OF THE
	POSSIBILITY OF SUCH DAMAGE.
*/



/*
 *	RISC-V instruction memory
 */



module instruction_memory(addr, out);
	input [31:0]		addr;
	output [31:0]		out;

	/*
	 *	Size the instruction memory.
	 *
	 *	(Bad practice: The constant should be a `define).
	 */
	 
	reg [31:0]		instruction_memory[0:2**10-1];

	/*
	 *	According to the "iCE40 SPRAM Usage Guide" (TN1314 Version 1.0), page 5:
	 *
	 *		"SB_SPRAM256KA RAM does not support initialization through device configuration."
	 *
	 *	The only way to have an initializable memory is to use the Block RAM.
	 *	This uses Yosys's support for nonzero initial values:
	 *
	 *		https://github.com/YosysHQ/yosys/commit/0793f1b196df536975a044a4ce53025c81d00c7f
	 *
	 *	Rather than using this simulation construct (`initial`),
	 *	the design should instead use a reset signal going to
	 *	modules in the design.
	 */
	initial begin
		/*
		 *	read from "program.hex" and store the instructions in instruction memory
		 */
		$readmemh("programs/program.hex",instruction_memory);
	end

	assign out = instruction_memory[addr >> 2];
endmodule

verilog/hardware/processor/sail-simulation/improved_verilog/instruction_mem_tb.v
/*
	Authored 2018-2019, Ryan Voo.

	All rights reserved.
	Redistribution and use in source and binary forms, with or without
	modification, are permitted provided that the following conditions
	are met:

	*	Redistributions of source code must retain the above
		copyright notice, this list of conditions and the following
		disclaimer.

	*	Redistributions in binary form must reproduce the above
		copyright notice, this list of conditions and the following
		disclaimer in the documentation and/or other materials
		provided with the distribution.

	*	Neither the name of the author nor the names of its
		contributors may be used to endorse or promote products
		derived from this software without specific prior written
		permission.

	THIS SOFTWARE IS PROVIDED BY THE COPYRIGHT HOLDERS AND CONTRIBUTORS
	"AS IS" AND ANY EXPRESS OR IMPLIED WARRANTIES, INCLUDING, BUT NOT
	LIMITED TO, THE IMPLIED WARRANTIES OF MERCHANTABILITY AND FITNESS
	FOR A PARTICULAR PURPOSE ARE DISCLAIMED. IN NO EVENT SHALL THE
	COPYRIGHT OWNER OR CONTRIBUTORS BE LIABLE FOR ANY DIRECT, INDIRECT,
	INCIDENTAL, SPECIAL, EXEMPLARY, OR CONSEQUENTIAL DAMAGES (INCLUDING,
	BUT NOT LIMITED TO, PROCUREMENT OF SUBSTITUTE GOODS OR SERVICES;
	LOSS OF USE, DATA, OR PROFITS; OR BUSINESS INTERRUPTION) HOWEVER
	CAUSED AND ON ANY THEORY OF LIABILITY, WHETHER IN CONTRACT, STRICT
	LIABILITY, OR TORT (INCLUDING NEGLIGENCE OR OTHERWISE) ARISING IN
	ANY WAY OUT OF THE USE OF THIS SOFTWARE, EVEN IF ADVISED OF THE
	POSSIBILITY OF SUCH DAMAGE.
*/


module instruction_RAM_mem_tb();

reg [31:0]		addr;
wire [31:0]		out;
/*
wire [1:0] check0;
wire [1:0] check1;
wire [1:0] check2;
wire [1:0] check3;
wire [1:0] check4;
*/
instruction_memory irm(
	.addr(addr), 
	.out(out)
	/*
	.check0(check0),
	.check1(check1),
	.check2(check2),
	.check3(check3),
	.check4(check4)
	*/
);
localparam period = 2;  //2s

//simulation
initial begin
	addr = 32'h0;
end	
always 
begin
	$dumpfile ("instruction_mem.vcd");
	$dumpvars;

	//write bytes
	addr = 32'h08;
	#period;
	addr = 32'h0C;

	#period;
	addr = 32'h10;

	#period;
	addr = 32'h14;

	#period;
	addr = 32'h3DC;
	#period;

	addr = 32'h3E0;
	#period;
	
	addr = 32'h3E4;
	#period;

	addr = 32'h3E8;
	#period;
	
	addr = 32'h3EC;
	#period;
	addr = 32'h3F0;
	#period;

	addr = 32'h3F4;
	#period;
	$finish;

end

endmodule

verilog/hardware/processor/sail-simulation/improved_verilog/instruction_mem.vcd
$date
	Sat Jun  5 13:24:25 2021
$end
$version
	Icarus Verilog
$end
$timescale
	1s
$end
$scope module instruction_RAM_mem_tb $end
$var wire 32 ! out [31:0] $end
$var reg 32 " addr [31:0] $end
$scope module irm $end
$var wire 32 # addr [31:0] $end
$var wire 32 $ out [31:0] $end
$upscope $end
$upscope $end
$enddefinitions $end
#0
$dumpvars
b1000000000000010000000100010011 $
b1000 #
b1000 "
b1000000000000010000000100010011 !
$end
#2
b111101010000000000000001101111 !
b111101010000000000000001101111 $
b1100 "
b1100 #
#4
b11111110000000010000000100010011 !
b11111110000000010000000100010011 $
b10000 "
b10000 #
#6
b100010010111000100011 !
b100010010111000100011 $
b10100 "
b10100 #
#8
b1000000001100111 !
b1000000001100111 $
b1111011100 "
b1111011100 #
#10
b11111111000000010000000100010011 !
b11111111000000010000000100010011 $
b1111100000 "
b1111100000 #
#12
b100010010011000100011 !
b100010010011000100011 $
b1111100100 "
b1111100100 #
#14
b100000010010010000100011 !
b100000010010010000100011 $
b1111101000 "
b1111101000 #
#16
b1000000010000010000010011 !
b1000000010000010000010011 $
b1111101100 "
b1111101100 #
#18
b1011110110111 !
b1011110110111 $
b1111110000 "
b1111110000 #
#20
b100000001111010011110000011 !
b100000001111010011110000011 $
b1111110100 "
b1111110100 #
